{
  "aadres": "aadress",
  "aadresi": "aadressi",
  "aadresiga": "aadressiga",
  "aadresil": "aadressil",
  "aadresile": "aadressile",
  "aadressel": "aadressil",
  "aadressill": "aadressil",
  "aadris": "aadress",
  "aadrisel": "aadressil",
  "aadrisil": "aadressil",
  "aadrissil": "aadressil",
  "aagres": "aadress",
  "aaru": "aru",
  "aastade": "aastate",
  "aastadel": "aastatel",
  "aastades": "aastates",
  "aastapaeva": "aastapäeva",
  "aatat": "aastat",
  "abielub": "abiellub",
  "abielunud": "abiellunud",
  "abielused": "abielus",
  "abieluses": "abielus",
  "abielusin": "abiellusin",
  "abieluvad": "abielluvad",
  "abikasa": "abikaasa",
  "abikasaga": "abikaasaga",
  "abikassa": "abikaasa",
  "abit": "abi",
  "abivad": "aitavad",
  "absolutselt": "absoluutselt",
  "administrator": "administraator",
  "administratorina": "administraatorina",
  "adres": "aadress",
  "adresil": "aadressil",
  "adress": "aadress",
  "adressi": "aadressi",
  "adressil": "aadressil",
  "adressile": "aadressile",
  "adrissel": "aadressil",
  "aegaga": "ajaga",
  "aerobika": "aeroobika",
  "agentina": "agendina",
  "agresiivne": "agressiivne",
  "ahjakütte": "ahjuküte",
  "ahjukuttega": "ahjuküttega",
  "ahjuküt": "ahjuküte",
  "ahjukütega": "ahjuküttega",
  "ahjukütt": "ahjuküte",
  "ahjuküttet": "ahjukütet",
  "ahjusse": "ahju",
  "aidab": "aitab",
  "aidama": "aitama",
  "aidatan": "aitan",
  "aidate": "aitate",
  "aidavad": "aitavad",
  "aiga": "aega",
  "aijas": "aias",
  "ainud": "ainult",
  "ainul": "ainult",
  "ainuld": "ainult",
  "aitada": "aidata",
  "aitah": "aitäh",
  "aitanud": "aidanud",
  "aite": "aitäh",
  "aj": "ja",
  "ajadel": "aegadel",
  "ajadest": "aegadest",
  "ajakirjanikkuna": "ajakirjanikuna",
  "ajalehedest": "ajalehtedest",
  "ajalehteid": "ajalehti",
  "ajalehtidest": "ajalehtedest",
  "ajalood": "ajalugu",
  "ajamaal": "aiamaal",
  "akan": "hakkan",
  "aki": "äkki",
  "akkab": "hakkab",
  "akkame": "hakkame",
  "akkan": "hakkan",
  "akkas": "hakkas",
  "akkavad": "hakkavad",
  "akki": "äkki",
  "aknade": "akende",
  "aktivne": "aktiivne",
  "aktsentiga": "aktsendiga",
  "aktualne": "aktuaalne",
  "alatest": "alates",
  "alganud": "alanud",
  "alkogoli": "alkoholi",
  "alkohool": "alkoholi",
  "alkohooli": "alkoholi",
  "alkohoolijoogid": "alkoholijoogid",
  "allati": "alati",
  "amerikas": "ameerikas",
  "ameriklane": "ameeriklane",
  "anab": "annab",
  "anan": "annan",
  "anavad": "annavad",
  "andab": "annab",
  "andakse": "antakse",
  "annas": "andis",
  "antik": "antiik",
  "antis": "andis",
  "antsid": "andsid",
  "apelsiini": "apelsini",
  "apelsiinid": "apelsinid",
  "apparat": "aparaat",
  "aranenud": "arenenud",
  "argumentid": "argumendid",
  "arikkel": "artikkel",
  "aripäeval": "äripäeval",
  "arkan": "ärkan",
  "armistad": "armastad",
  "armistan": "armastan",
  "arstirohted": "arstirohte",
  "arstirohtid": "arstirohud",
  "arti": "arsti",
  "artiikel": "artikkel",
  "artiiklit": "artiklit",
  "artikel": "artikkel",
  "artikkli": "artikli",
  "aruanned": "aruanded",
  "arusaada": "aru saada",
  "arvada": "arvata",
  "arvades": "arvates",
  "arvat": "arvan",
  "arvatan": "arvan",
  "arvatest": "arvates",
  "arvutidega": "arvutitega",
  "arä": "ära",
  "asiad": "asjad",
  "asjaid": "asju",
  "asperiini": "aspiriini",
  "aspirini": "aspiriini",
  "assortiment": "sortiment",
  "astast": "aastast",
  "astat": "aastat",
  "ausune": "aus",
  "autoid": "autosid",
  "autosi": "autosid",
  "avari": "avarii",
  "baarisse": "baari",
  "bakalauruse": "bakalaureuse",
  "balett": "ballett",
  "baletti": "balletti",
  "balsam": "palsam",
  "bananid": "banaanid",
  "baris": "baaris",
  "batareid": "patareid",
  "beez": "beež",
  "biletid": "piletid",
  "bokaalid": "pokaalid",
  "brutto": "bruto",
  "busiga": "bussiga",
  "bürotooli": "bürootooli",
  "depression": "depressioon",
  "detektivid": "detektiivid",
  "detsembreni": "detsembrini",
  "diagraam": "diagramm",
  "diagraamist": "diagrammist",
  "diploom": "diplom",
  "diploomi": "diplomi",
  "diskussion": "diskussioon",
  "diskussionid": "diskussioonid",
  "divaan": "diivan",
  "divaanil": "diivanil",
  "divan": "diivan",
  "divani": "diivani",
  "divanil": "diivanil",
  "divanile": "diivanile",
  "dokumendide": "dokumentide",
  "dokumentid": "dokumendid",
  "ebavõimalik": "võimatu",
  "eeksamid": "eksamid",
  "eesimene": "esimene",
  "eesmaspäeval": "esmaspäeval",
  "eesmaspäevast": "esmaspäevast",
  "eesmärg": "eesmärk",
  "eestalaseks": "eestlaseks",
  "eeste": "eesti",
  "eestikeel": "eesti keel",
  "eestikeele": "eesti keele",
  "eestikeeles": "eesti keeles",
  "eestikeelt": "eesti keelt",
  "eestikelt": "eesti keelt",
  "eestima": "eestimaa",
  "eestirahva": "eesti rahva",
  "eestirahvas": "eesti rahvas",
  "eestlasid": "eestlasi",
  "effektiivne": "efektiivne",
  "effektivne": "efektiivne",
  "ehitusmaterjaalid": "ehitusmaterjalid",
  "ej": "ei",
  "ekonoomika": "ökonoomika",
  "eksaam": "eksam",
  "eksaamid": "eksamid",
  "ekskursion": "ekskursioon",
  "ekskursioni": "ekskursiooni",
  "elamistuba": "elutuba",
  "elanikkest": "elanikest",
  "elanikudel": "elanikel",
  "elanikudele": "elanikele",
  "elanikudest": "elanikest",
  "elanikuid": "elanikke",
  "elanikut": "elanikud",
  "elanikute": "elanike",
  "elanikutega": "elanikega",
  "elanikutel": "elanikel",
  "elanikutele": "elanikele",
  "elanikutest": "elanikest",
  "elista": "helista",
  "elmine": "eelmine",
  "elmisel": "eelmisel",
  "eluda": "elada",
  "elut": "elu",
  "elutemp": "elutempo",
  "elutubas": "elutoas",
  "emeil": "meil",
  "enast": "ennast",
  "eneergia": "energia",
  "eneergiat": "energiat",
  "englise": "inglise",
  "ennetamse": "ennetamise",
  "epan": "pean",
  "erialat": "eriala",
  "eriallal": "erialal",
  "eriliseid": "erilisi",
  "erinavad": "erinevad",
  "erinevade": "erinevate",
  "erinevadel": "erinevatel",
  "erinevades": "erinevates",
  "erinivad": "erinevad",
  "eritti": "eriti",
  "esemesel": "esimesel",
  "esialgul": "esialgu",
  "esimeni": "esimene",
  "esimine": "esimene",
  "esimisel": "esimesel",
  "esmapäeval": "esmaspäeval",
  "esmapäevast": "esmaspäevast",
  "esmaspaev": "esmaspäev",
  "esmaspaeval": "esmaspäeval",
  "esmaspaevast": "esmaspäevast",
  "esmastpäevast": "esmaspäevast",
  "estis": "eestis",
  "estlased": "eestlased",
  "estlaste": "eestlaste",
  "estlastega": "eestlastega",
  "ettendus": "etendus",
  "ettenduse": "etenduse",
  "ettendusel": "etendusel",
  "ettendusi": "etendusi",
  "ettendust": "etendust",
  "ettevalmistada": "ette valmistada",
  "ettevatlik": "ettevaatlik",
  "ettevatlikult": "ettevaatlikult",
  "ettevõted": "ettevõtted",
  "ettevõteid": "ettevõtteid",
  "ettevõtes": "ettevõttes",
  "ettevõtlikkud": "ettevõtlikud",
  "ettevõtlikuid": "ettevõtlikke",
  "ettevõtta": "ette võtta",
  "ettevõttedes": "ettevõtetes",
  "ettevõttete": "ettevõtete",
  "europasse": "Euroopasse",
  "fakultet": "fakulteet",
  "fakultetis": "fakulteedis",
  "festivaale": "festivale",
  "festivaalid": "festivalid",
  "filmit": "filmi",
  "firmaid": "firmasid",
  "firmasi": "firmasid",
  "firmi": "firma",
  "firmis": "firmas",
  "formistamine": "vormistamine",
  "fotoapparat": "fotoaparaat",
  "fotograafit": "fotograafi",
  "fotografina": "fotograafina",
  "frantsuse": "prantsuse",
  "gaasikuttega": "gaasiküttega",
  "gaasikütt": "gaasiküte",
  "garanti": "garantii",
  "garantiit": "garantiid",
  "glaas": "klaas",
  "graadi": "kraadi",
  "graamatika": "grammatika",
  "grafik": "graafik",
  "gramaatika": "grammatika",
  "gramaatikat": "grammatikat",
  "gramatika": "grammatika",
  "grammaatika": "grammatika",
  "gratsia": "graatsia",
  "grippis": "gripis",
  "gruppa": "grupp",
  "gruppid": "grupid",
  "gruppiga": "grupiga",
  "gruppil": "grupil",
  "gruppile": "grupile",
  "gruppis": "grupis",
  "gruppist": "grupist",
  "gruppitöö": "grupitöö",
  "gümnasiumi": "gümnaasiumi",
  "gümnasiumis": "gümnaasiumis",
  "haiglades": "haiglates",
  "hakab": "hakkab",
  "hakan": "hakkan",
  "hakas": "hakkas",
  "hakasid": "hakkasid",
  "hakasin": "hakkasin",
  "hakavad": "hakkavad",
  "hakkada": "hakata",
  "hakkage": "hakake",
  "hakkanud": "hakanud",
  "hakkata": "hakata",
  "hakkatakse": "hakatakse",
  "hakkati": "hakati",
  "halbad": "halvad",
  "halp": "halb",
  "harvasti": "harva",
  "hasti": "hästi",
  "heameelne": "heatujuline",
  "helesta": "helista",
  "helestan": "helistan",
  "heliloojade": "heliloojate",
  "hellista": "helista",
  "hellistada": "helistada",
  "hellistage": "helistage",
  "hellistan": "helistan",
  "hesti": "hästi",
  "hiljam": "hiljem",
  "hiljati": "hiljuti",
  "hinad": "hinnad",
  "hingada": "hingata",
  "hinnab": "hindab",
  "hinnade": "hindade",
  "hinnadega": "hindadega",
  "hinnadest": "hindadest",
  "hinnaid": "hindu",
  "hinnavad": "hindavad",
  "hinned": "hinded",
  "hobbi": "hobi",
  "hobbid": "hobid",
  "hojan": "hoian",
  "holitseb": "hoolitseb",
  "holitseda": "hoolitseda",
  "holitsema": "hoolitsema",
  "homikul": "hommikul",
  "homikust": "hommikust",
  "hooaga": "hooga",
  "hooguga": "hooga",
  "hoome": "homme",
  "hotelis": "hotellis",
  "hotellisse": "hotelli",
  "hottelis": "hotellis",
  "hukuvad": "hukkuvad",
  "hulg": "hulk",
  "hulgimüükiga": "hulgimüügiga",
  "hulkas": "hulgas",
  "hund": "hunt",
  "huumorimeelne": "humoorikas",
  "huuvitav": "huvitav",
  "huvitamaks": "huvitavamaks",
  "huvitavait": "huvitavaid",
  "huvitavi": "huvitavaid",
  "häiritab": "häirib",
  "häit": "häid",
  "idea": "idee",
  "ideea": "idee",
  "ideet": "ideed",
  "ie": "ei",
  "ika": "ikka",
  "ilis": "ilus",
  "ilusade": "ilusate",
  "ilused": "ilusad",
  "inemene": "inimene",
  "inemesed": "inimesed",
  "inemesele": "inimesele",
  "inemesi": "inimesi",
  "inemest": "inimest",
  "inemisi": "inimesi",
  "infod": "infot",
  "informatsion": "informatioon",
  "informatsioni": "informatsiooni",
  "informatsioone": "informatsiooni",
  "infotehnologia": "infotehnoloogia",
  "inglisekeele": "inglise keele",
  "inglisekeeles": "inglise keeles",
  "inglisekeelt": "inglise keelt",
  "inglish": "inglise",
  "inglisse": "inglise",
  "inimen": "inimene",
  "inimesedele": "inimestele",
  "inimeseid": "inimesi",
  "inimesile": "inimestele",
  "inimestedega": "inimestega",
  "inimine": "inimene",
  "inimise": "inimese",
  "inimised": "inimesed",
  "inimisega": "inimesega",
  "inimiseid": "inimesi",
  "inimisel": "inimesel",
  "inimisele": "inimesele",
  "inimisi": "inimesi",
  "inimiste": "inimeste",
  "inimistega": "inimestega",
  "inimistel": "inimestel",
  "inimste": "inimeste",
  "inlise": "inglise",
  "inseneeri": "inseneri",
  "inseneeriks": "isneneriks",
  "inseneerina": "insenerina",
  "insineer": "insener",
  "instrumentid": "instrumendid",
  "interneet": "internet",
  "interneetis": "internetis",
  "internetit": "internetti",
  "internettis": "internetis",
  "iseennale": "iseendale",
  "iseseisav": "iseseisev",
  "jaab": "jääb",
  "jaada": "jääda",
  "jaanud": "jäänud",
  "jaavad": "jäävad",
  "jai": "jäi",
  "jaid": "jäid",
  "jalakäiad": "jalakäijad",
  "jalgas": "jalas",
  "jalgida": "jälgida",
  "jalgin": "jälgin",
  "jalgrataga": "jalgrattaga",
  "jalgsin": "jalutasin",
  "jalle": "jälle",
  "jaok": "jaoks",
  "jarel": "järel",
  "jarele": "järele",
  "jargi": "järgi",
  "jargmine": "järgmine",
  "jargmise": "järgmise",
  "jargmised": "järgmised",
  "jargmiseks": "järgmiseks",
  "jargmisel": "järgmisel",
  "jargmisesse": "järgmisesse",
  "jargmisse": "järgmisse",
  "jargmist": "järgmist",
  "jarv": "järv",
  "jarve": "järve",
  "jatab": "jätab",
  "jatkab": "jätkab",
  "jatkas": "jätkas",
  "jatku": "jätku",
  "jatkub": "jätkub",
  "jatkus": "jätkus",
  "jatnud": "jätnud",
  "joksul": "jooksul",
  "jome": "joome",
  "jooksemine": "jooksmine",
  "jooksib": "jooksis",
  "jooksivad": "jooksid",
  "jooksta": "joosta",
  "jubeli": "juubeli",
  "juhtumistöö": "juhutöö",
  "julil": "juulil",
  "julis": "juulis",
  "junil": "juunil",
  "jures": "juures",
  "jurvilja": "juurvilja",
  "juttud": "jutud",
  "juuasime": "jõime",
  "juuba": "juba",
  "juubilei": "juubel",
  "juuksega": "juustega",
  "juuksla": "juuksur",
  "juuridilised": "juriidilised",
  "juurist": "jurist",
  "jägada": "jagada",
  "jäib": "jäi",
  "jälgsi": "jalgsi",
  "jälutan": "jalutan",
  "jäoks": "jaoks",
  "järvid": "järved",
  "jätkada": "jätkata",
  "jäärgi": "järgi",
  "jäärgmisel": "järgmisel",
  "jäätku": "jätku",
  "jööksul": "jooksul",
  "jööma": "jooma",
  "jööme": "joome",
  "jöön": "joon",
  "jöövad": "joovad",
  "jürde": "juurde",
  "jüüa": "juua",
  "jüürde": "juurde",
  "jüüres": "juures",
  "kaa": "ka",
  "kaalis": "kallis",
  "kaamina": "kamina",
  "kabinetides": "kabinettides",
  "kadub": "kaob",
  "kaebata": "kaevata",
  "kahekorrulised": "kahekorruselised",
  "kaheksakümme": "kaheksakümne",
  "kaheksateisteni": "kaheksateistkümneni",
  "kahekumne": "kahekümne",
  "kahekümmne": "kahekümne",
  "kahetuhande": "kahe tuhande",
  "kahjus": "kahjuks",
  "kaib": "käib",
  "kaima": "käima",
  "kaime": "käime",
  "kaimine": "käimine",
  "kainud": "käinud",
  "kaisime": "käisime",
  "kaisin": "käisin",
  "kaivad": "käivad",
  "kakskummend": "kakskümmend",
  "kakskümend": "kakskümmend",
  "kakskümment": "kakskümmend",
  "kaksteis": "kaksteist",
  "kaksteistest": "kaheteistkümnest",
  "kaksteistkümnest": "kaheteistkümnest",
  "kakstuhad": "kaks tuhat",
  "kakstuhat": "kaks tuhat",
  "kalis": "kallis",
  "kallised": "kallid",
  "kamera": "kaamera",
  "kamiin": "kamin",
  "kamiini": "kamina",
  "kamini": "kamina",
  "kandidaad": "kandidaat",
  "kandidaatur": "kandidatuur",
  "kandidad": "kandidaat",
  "kandidadile": "kandidaadile",
  "kandidat": "kandidaat",
  "kandidatid": "kandidaadid",
  "kanditaatidelt": "kandidaatidelt",
  "kappis": "kapis",
  "kardanud": "kartnud",
  "kardasin": "kartsin",
  "kardis": "kartis",
  "kardke": "kartke",
  "kardsin": "kartsin",
  "kasaaegne": "kaasaegne",
  "kasaaegsed": "kaasaegsed",
  "kasulikut": "kasulikku",
  "kasut": "kasu",
  "kasvaneb": "kasvab",
  "katalogi": "kataloogi",
  "katalogide": "kataloogide",
  "katolik": "katoliku",
  "kaubade": "kaupade",
  "kaubadega": "kaupadega",
  "kauplusese": "kauplusesse",
  "keedagi": "kedagi",
  "keedasin": "keetsin",
  "keegil": "kellelgi",
  "keegile": "kellelegi",
  "keell": "kell",
  "keelle": "keele",
  "keerage": "keerake",
  "keetan": "keedan",
  "kegi": "keegi",
  "keigi": "keegi",
  "kekslinnas": "kesklinnas",
  "kela": "kella",
  "keles": "keeles",
  "kellegiga": "kellegagi",
  "kellegile": "kellelegi",
  "kellt": "keelt",
  "keruline": "keeruline",
  "keskes": "keskel",
  "kesklinas": "kesklinnas",
  "kesklinnasse": "kesklinna",
  "keskonda": "keskkonda",
  "keskonna": "keskkonna",
  "keskonnas": "keskkonnas",
  "keskpäevaeina": "keskpäevaeine",
  "keskütte": "keskküte",
  "kestas": "kestis",
  "kidas": "kuidas",
  "kiiremine": "kiiremini",
  "kijra": "kirja",
  "kilometri": "kilomeetri",
  "kilometrit": "kilomeetrit",
  "kindalsti": "kindlasti",
  "kingisid": "kinkisid",
  "kingisime": "kinkisime",
  "kingitada": "kinkida",
  "kingitame": "kingime",
  "kingitas": "kinkis",
  "kingituseid": "kingitusi",
  "kinglasti": "kindlasti",
  "kinkin": "kingin",
  "kinkitakse": "kingitakse",
  "kinkivad": "kingivad",
  "kinnos": "kinos",
  "kinnosse": "kinno",
  "kinot": "kino",
  "kiremini": "kiiremini",
  "kiresti": "kiiresti",
  "kirjanikude": "kirjanike",
  "kirjanikut": "kirjanikku",
  "kirjanikutest": "kirjanikest",
  "kirjuda": "kirjutada",
  "kirjutakse": "kirjutatakse",
  "kitsades": "kitsastes",
  "klassisse": "klassi",
  "klaveerit": "klaverit",
  "kleitid": "kleidid",
  "kliend": "klient",
  "kliendidega": "klientidega",
  "kliendidele": "klientidele",
  "kliendit": "kliendid",
  "klienditega": "klientidega",
  "klienditele": "klientidele",
  "klienditenindaja": "klienditeenindaja",
  "klientid": "kliendid",
  "klientiga": "kliendiga",
  "klientile": "kliendile",
  "klubbisse": "klubisse",
  "kluubi": "klubi",
  "kluubis": "klubis",
  "kodis": "kodus",
  "kodukindluste": "kodukindlustuse",
  "kodunetööd": "kodutööd",
  "koduneülesandeid": "koduülesandeid",
  "kohades": "kohtades",
  "kohtanud": "kohanud",
  "kohtumini": "kohtumiseni",
  "kohtusemini": "kohtumiseni",
  "kohve": "kohvi",
  "kohvid": "kohvi",
  "kohvikuses": "kohvikus",
  "koike": "kõike",
  "kojju": "koju",
  "kojus": "kodus",
  "kojust": "kodust",
  "kokkana": "kokana",
  "kokkukvõtte": "kokkuvõtte",
  "kokkuleppime": "lepime kokku",
  "kokkume": "kohtume",
  "kokkusaades": "kokku saades",
  "kokkuvõteks": "kokkuvõtteks",
  "kolane": "kollane",
  "koleeg": "kolleeg",
  "koleegid": "kolleegid",
  "koleegidega": "kolleegidega",
  "kolektiivis": "kollektiivis",
  "kolitus": "koolitus",
  "kolledzis": "kolledžis",
  "kolleega": "kolleeg",
  "kolleg": "kolleeg",
  "kollega": "kolleeg",
  "kollege": "kolleege",
  "kollegid": "kolleegid",
  "kollegide": "kolleegide",
  "kollegidega": "kolleegidega",
  "kollegidele": "kolleegidele",
  "kollegiga": "kolleegiga",
  "kollegile": "kolleegile",
  "kollektiv": "kollektiiv",
  "kollektivis": "kollektiivis",
  "kolmaks": "kolmeks",
  "kolmal": "kolmel",
  "kolmapaev": "kolmapäev",
  "kolmapaeval": "kolmapäeval",
  "kolmapäevati": "kolmapäeviti",
  "kolmapäevini": "kolmapäevani",
  "kolmapävani": "kolmapäevani",
  "kolmaspäeval": "kolmapäeval",
  "kolmast": "kolmest",
  "kolmepäeval": "kolmapäeval",
  "kolmepäevani": "kolmapäevani",
  "kolmkummend": "kolmkümmend",
  "kolmpäev": "kolmapäev",
  "kolmteiseni": "kolmeteistkümneni",
  "kolmteisteni": "kolmeteistkümneni",
  "kolmtoaline": "kolmetoaline",
  "kolmverand": "kolmveerand",
  "komandeeringuse": "komandeeringusse",
  "komandering": "komandeering",
  "komanderingus": "komandeeringus",
  "komanderingusse": "komandeeringusse",
  "kombet": "kombed",
  "komisjoon": "komisjon",
  "kommandeeringusse": "komandeeringusse",
  "kommed": "kombed",
  "kompjuteriga": "kompuutriga",
  "kompuuteriga": "kompuutriga",
  "konferentsi": "konverentsi",
  "konkretselt": "konkreetselt",
  "konkurentsioon": "konkurents",
  "konkurs": "konkurss",
  "konkurssid": "konkursid",
  "konkurssil": "konkursil",
  "konkurssile": "konkursile",
  "konkurssis": "konkursis",
  "konserdi": "kontserdi",
  "konserdil": "kontserdil",
  "konserdile": "kontserdile",
  "konsert": "kontsert",
  "kontaaktne": "kontaktne",
  "kontaktandmend": "kontaktandmed",
  "kontakteerida": "kontakteeruda",
  "kontakteid": "kontakte",
  "kontaktida": "kontakteeruda",
  "kontaktitelefon": "kontakttelefon",
  "kontorides": "kontorites",
  "kontserd": "kontsert",
  "kontserditel": "kontsertidel",
  "kontsertid": "kontserdid",
  "kontsertil": "kontserdil",
  "kontsertile": "kontserdile",
  "kontsertis": "kontserdis",
  "kontsertit": "kontserti",
  "konverent": "konverents",
  "koodus": "kodus",
  "kooku": "kokku",
  "koolida": "kolida",
  "koolise": "kooli",
  "koolisime": "kolisime",
  "koord": "kord",
  "koordinaalselt": "kardinaalselt",
  "koorter": "korter",
  "koosvibimine": "koosviibimine",
  "koosööpartnerile": "koostööpartnerile",
  "koras": "korras",
  "koridooris": "koridoris",
  "korjada": "korjata",
  "kormus": "koormus",
  "korraldakse": "korraldatakse",
  "korterides": "korterites",
  "korterise": "korterisse",
  "korval": "kõrval",
  "kosmetika": "kosmeetika",
  "kosmetikat": "kosmeetikat",
  "kottiga": "kotiga",
  "kottisse": "kotti",
  "kraanikaus": "kraanikauss",
  "kroni": "krooni",
  "kroodi": "kraadi",
  "kudagi": "kuidagi",
  "kueni": "kuueni",
  "kuida": "kuidas",
  "kuin": "kui",
  "kukkub": "kukub",
  "kulas": "külas",
  "kulasin": "kuulasin",
  "kulata": "kuulata",
  "kuljest": "küljest",
  "kulmetanud": "külmetanud",
  "kulsin": "kuulsin",
  "kulturi": "kultuuri",
  "kulturimaja": "kultuurimaja",
  "kulturis": "kultuuris",
  "kunagil": "kunagi",
  "kurbad": "kurvad",
  "kuritegija": "kurjategija",
  "kuritegijad": "kurjategijad",
  "kuritegijaks": "kurjategijaks",
  "kuritegijat": "kurjategijat",
  "kurs": "kursus",
  "kursud": "kursused",
  "kursudes": "kursustel",
  "kursusule": "kursusele",
  "kurvamalt": "kurvemalt",
  "kusepuu": "kuusepuu",
  "kusis": "küsis",
  "kusk": "kuusk",
  "kuskel": "kuskil",
  "kussteist": "kuusteist",
  "kusteist": "kuusteist",
  "kuulada": "kuulata",
  "kuuland": "kuulanud",
  "kuultur": "kultuur",
  "kuulturi": "kultuuri",
  "kuursused": "kursused",
  "kuuskümend": "kuuskümmend",
  "kvaliteed": "kvaliteet",
  "kvaliteetiga": "kvaliteediga",
  "kvalitetne": "kvaliteetne",
  "kõge": "kõige",
  "kõhvi": "kohvi",
  "kõig": "kõik",
  "kõiged": "kõik",
  "kõigede": "kõikide/kõigi",
  "kõigedel": "kõikidel/kõigil",
  "kõigedele": "kõikidele/kõigile",
  "kõigem": "kõige",
  "kõigidega": "kõikidega/kõigiga",
  "kõigidel": "kõigil",
  "kõigidele": "kõigile",
  "kõigides": "kõigis",
  "kõigidest": "kõikidest/kõigist",
  "kõigipealt": "kõigepealt",
  "kõikede": "kõikide/kõigi",
  "kõikel": "kõigil",
  "kõikele": "kõigile",
  "kõikest": "kõigest",
  "kõikile": "kõigile",
  "kõikke": "kõike",
  "kõk": "kõik",
  "kõke": "kõike",
  "kõrkharidust": "kõrgharidus",
  "kõrvpall": "korvpall",
  "kõrvpalli": "korvpalli",
  "käeme": "käime",
  "käevad": "käivad",
  "käind": "käinud",
  "käja": "käia",
  "kämpingis": "kämpingus",
  "käsiti": "kästi/käsitsi",
  "käsitööt": "käsitööd",
  "käskitakse": "käsitakse",
  "käteratikud": "käterätikud",
  "kättega": "kätega",
  "kätteriiete": "katteriiete",
  "kättes": "kätes",
  "kättesaada": "kättesaadav",
  "kääs": "käes",
  "köige": "kõige",
  "köik": "kõik",
  "körge": "kõrge",
  "köögisse": "kööki",
  "köökis": "köögis",
  "kül": "küll",
  "külaste": "külaliste",
  "küllalised": "külalised",
  "küllas": "külas",
  "küllasse": "külla",
  "küllastada": "külastada",
  "küllastajad": "külastajad",
  "külmkappis": "külmkapis",
  "kümend": "kümmend",
  "kümment": "kümmend",
  "küsimuseid": "küsimusi",
  "küsitlenutest": "küsitletutest",
  "küsitlututest": "küsitletutest",
  "küttame": "kütame",
  "küttet": "kütet",
  "küttevad": "köetakse",
  "küttus": "kütus",
  "küttuse": "kütuse",
  "küttust": "kütust",
  "küül": "küll",
  "küülas": "külas",
  "labu": "laabu",
  "laenada": "laenata",
  "laheb": "läheb",
  "lahedal": "lähedal",
  "laheme": "lähme",
  "lahen": "lähen",
  "lahevad": "lähevad",
  "lahme": "lähme",
  "lainud": "läinud",
  "laksin": "läksin",
  "lampid": "lambid",
  "lapsedega": "lastega",
  "lapsedel": "lastel",
  "lapsedele": "lastele",
  "lapseid": "lapsi",
  "lapsepõlvast": "lapsepõlvest",
  "lapsevad": "lapsed",
  "lapsid": "lapsi",
  "lapsiga": "lapsega",
  "lapsile": "lapsele",
  "lasteaijas": "lasteaias",
  "lasteaja": "lasteaia",
  "lasteajad": "lasteaiad",
  "lasteajas": "lasteaias",
  "lasteajast": "lasteaiast",
  "lauapäeva": "laupäeva",
  "lauapäeval": "laupäeval",
  "lauapäevast": "laupäevast",
  "laulada": "laulda",
  "laulades": "lauldes",
  "laulaga": "lauluga",
  "laulama": "laulda",
  "laulamine": "laulmine",
  "laulapäev": "laupäev",
  "laulapäeval": "laupäeval",
  "laulas": "laulis",
  "laulasid": "laulsid",
  "laulasime": "laulsime",
  "laulasin": "laulsin",
  "laulatakse": "lauldakse",
  "laulav": "laulev",
  "laulde": "laulude",
  "laulme": "laulame",
  "laulpäeval": "laupäeval",
  "laulti": "lauldi",
  "laulumine": "laulmine",
  "laulupeode": "laulupidude",
  "laulupeodel": "laulupidudel",
  "laulupeodest": "laulupidudest",
  "laulupeosid": "laulupidusid",
  "laulupidud": "laulupeod",
  "laulurahv": "laulurahvas",
  "lauluvad": "laulavad",
  "laupaev": "laupäev",
  "laupaeva": "laupäeva",
  "laupaeval": "laupäeval",
  "laupaevani": "laupäevani",
  "laupäevati": "laupäeviti",
  "laupäival": "laupäeval",
  "laupäval": "laupäeval",
  "leidab": "leiab",
  "leidad": "leiad",
  "leidan": "leian",
  "leidavad": "leiavad",
  "leidi": "leiti",
  "leidsis": "leidis",
  "leija": "leida",
  "leinud": "leidnud",
  "leisime": "leidsime",
  "leitsin": "leidsin",
  "lektoorid": "lektorid",
  "lemik": "lemmik",
  "lendma": "lendama",
  "lennujaamasse": "lennujaama",
  "lennukjaam": "lennujaam",
  "lensime": "lendasime",
  "lepida": "leppida",
  "leppime": "lepime",
  "lepping": "leping",
  "levitud": "levinud",
  "lihtnea": "lihtne",
  "lihtsem": "lihtsam",
  "liiged": "liikmed",
  "liikmet": "liikmed",
  "liikub": "liigub",
  "liiled": "lilled",
  "liingile": "lingile",
  "liisada": "lisada",
  "liisaks": "lisaks",
  "liisaminuti": "lisaminuti",
  "liitumaksu": "liitumismaksu",
  "liivakääpadesse": "liivakääbastesse",
  "liivirannad": "liivarannad",
  "lilleid": "lilli",
  "lillid": "lilled",
  "limonad": "limonaad",
  "limonadi": "limonaadi",
  "lindades": "linnades",
  "linnasse": "linna",
  "lisata": "lisada",
  "lobisime": "lobisesime",
  "lodan": "loodan",
  "loeda": "lugeda",
  "loema": "lugema",
  "loengudest": "loengutest",
  "loenud": "lugenud",
  "loesime": "lugesime",
  "loesin": "lugesin",
  "lomulikult": "loomulikult",
  "loodama": "loota",
  "loomaajas": "loomaaias",
  "loomaklinik": "loomakliinik",
  "loomilikult": "loomulikult",
  "loominguses": "loomingus",
  "lootan": "loodan",
  "lugeb": "loeb",
  "lugega": "lugeda",
  "lugeme": "loeme",
  "lugen": "loen",
  "lugeta": "lugeda",
  "lugisin": "lugesin",
  "lugupeatud": "lugupeetud",
  "lugupeetumisega": "lugupidamisega",
  "lugupeetut": "lugupeetud",
  "lugupetud": "lugupeetud",
  "lukkus": "lukus",
  "luugejad": "lugejad",
  "lõbused": "lõbusad",
  "lõbusevad": "lõbusad",
  "lõbutsime": "lõbutsesime",
  "lõpenud": "lõppenud",
  "lõpes": "lõppes",
  "lõpetasi": "lõpetasin",
  "lõpetuteks": "lõpetuseks",
  "lõpitamist": "lõpetamist",
  "lõpitasin": "lõpetasin",
  "lõppesin": "lõpetasin",
  "lõppetada": "lõpetada",
  "lõppetamist": "lõpetamist",
  "lõppetan": "lõpetan",
  "lõppetanud": "lõpetanud",
  "lõppetasin": "lõpetasin",
  "lõppuks": "lõpuks",
  "lõppul": "lõpul",
  "lõppuni": "lõpuni",
  "lõppus": "lõpus",
  "lõpude": "lõppude",
  "lõpunu": "lõpuni",
  "lõpuseks": "lõpetuseks",
  "lõun": "lõuna",
  "lõõbus": "lõbus",
  "läheda": "lähedal",
  "lähedamad": "lähedasemad",
  "lähedamaks": "lähedasemaks",
  "lähesime": "läksime",
  "lähesin": "läksin",
  "lähetal": "lähedal",
  "lähime": "läks",
  "läisk": "laisk",
  "läksib": "läheb",
  "läleb": "läheb",
  "läupäeval": "laupäeval",
  "lääbi": "läbi",
  "läänemast": "läänemaast",
  "lülitakse": "lülitatakse",
  "lüsikas": "lusikas",
  "lüülitada": "lülitada",
  "maakohtis": "maakohas",
  "maantel": "maanteel",
  "maastikuid": "maastikke",
  "magamatoas": "magamistoas",
  "magamiskotides": "magamiskottides",
  "magamiskottid": "magamiskotid",
  "magamiskottis": "magamiskotis",
  "magamistubas": "magamistoas",
  "magand": "maganud",
  "magistratuuri": "magistrantuuri",
  "magistratuuris": "magistrantuuris",
  "mahaarvata": "maha arvata",
  "mahlat": "mahla",
  "maijooksi": "maijooksu",
  "mailile": "meilile",
  "mailm": "maailm",
  "mailma": "maailma",
  "majat": "maja",
  "majju": "maju",
  "makaroonid": "makaronid",
  "maksasin": "maksin",
  "maksevad": "maksavad",
  "maksme": "maksame",
  "maleta": "mäleta",
  "mangib": "mängib",
  "manguasjad": "mänguasjad",
  "mantee": "maantee",
  "maratoon": "maraton",
  "martsil": "märtsil",
  "massaaz": "massaaž",
  "massaz": "massaaž",
  "massazi": "massaaži",
  "materiaali": "materjali",
  "materialne": "materiaalne",
  "mediast": "meediast",
  "meditsini": "meditsiini",
  "meeldisib": "meeldis",
  "meelelahetus": "meelelahutus",
  "meelelahustuse": "meelelahutuste",
  "meere": "mere",
  "meeres": "meres",
  "meesi": "mett",
  "meesiga": "meega",
  "mehanika": "mehaanika",
  "mehede": "meeste",
  "mehedega": "meestega",
  "mehedel": "meestel",
  "mehedele": "meestele",
  "mei": "meie",
  "meied": "meie",
  "meiel": "meil",
  "meiele": "meile",
  "meies": "meis",
  "meiest": "meist",
  "meiga": "meiega",
  "meiste": "meeste",
  "meistel": "meestel",
  "meje": "meie",
  "mejega": "meiega",
  "melde": "meelde",
  "meldi": "meeldi",
  "meldib": "meeldib",
  "meldis": "meeldis",
  "meldisin": "meeldib",
  "meldiv": "meeldiv",
  "meldivad": "meeldivad",
  "meleolu": "meeleolu",
  "melldib": "meeldib",
  "melle": "mulle",
  "menü": "menüü",
  "mereääres": "mere ääres",
  "mestel": "meestel",
  "metrit": "meetrit",
  "metroga": "metrooga",
  "migrantid": "migrandid",
  "miinu": "minu",
  "miinusid": "miinused",
  "miksri": "mikseri",
  "milal": "millal",
  "millesed": "millised",
  "milleseid": "milliseid",
  "millisi": "milliseid",
  "minevikut": "minevikku",
  "mingeit": "mingeid",
  "minimaalpalka": "miinimumpalka",
  "minimum": "miinimum",
  "minne": "minna",
  "minnesin": "läksin",
  "minulle": "minule",
  "minuseid": "miinuseid",
  "misugune": "missugune",
  "misugused": "missugused",
  "mita": "mida",
  "mitagi": "midagi",
  "mittu": "mitu",
  "mobiilitelefon": "mobiiltelefon",
  "mobiiltelefonit": "mobiiltelefoni",
  "mobiiltelefoon": "mobiiltelefon",
  "mobiiltelefooni": "mobiiltelefoni",
  "mobil": "mobiil",
  "mobill": "mobiil",
  "mobilltelefon": "mobiiltelefon",
  "mobilltelefoni": "mobiiltelefoni",
  "mobiltelefon": "mobiiltelefon",
  "mobiltelefoni": "mobiiltelefoni",
  "mobiltelefonid": "mobiiltelefonid",
  "momentid": "momendid",
  "momentil": "momendil",
  "moobiiltelefon": "mobiiltelefon",
  "moobil": "mobiil",
  "moobiltelefon": "mobiiltelefon",
  "mors": "morss",
  "mugab": "mugav",
  "mugavuseid": "mugavusi",
  "muigugi": "muidugi",
  "muinasjut": "muinasjutt",
  "muinasjuttud": "muinasjutud",
  "muljedest": "muljetest",
  "mun": "mu",
  "munu": "minu",
  "murdab": "murrab",
  "murdas": "murdis",
  "museumi": "muuseumi",
  "museumis": "muuseumis",
  "musikat": "muusikat",
  "muudaba": "muudab",
  "muugav": "mugav",
  "muugavad": "mugavad",
  "muuid": "muid",
  "muusikaalne": "musikaalne",
  "muusikad": "muusikat",
  "muusikalne": "musikaalne",
  "muusiumis": "muuseumis",
  "muut": "muud",
  "muutab": "muutub",
  "muutan": "muudan",
  "mõistav": "mõistev",
  "mõnekord": "mõnikord",
  "mõnid": "mõned",
  "mõnidel": "mõnedel",
  "mõnikorg": "nõnikord",
  "mõted": "mõtted",
  "mõtega": "mõttega",
  "mõteid": "mõtteid",
  "mõtes": "mõttes",
  "mõtetu": "mõttetu",
  "mõtleda": "mõtelda",
  "mõttedega": "mõtetega",
  "mõttelda": "mõtelda",
  "mägid": "mäed",
  "mänguid": "mänge",
  "märatud": "määratud",
  "märgasin": "märkasin",
  "märkanud": "märganud",
  "märkata": "märkida",
  "määleta": "mäleta",
  "määletan": "mäletan",
  "möjutanud": "mõjutanud",
  "mööbil": "mööbel",
  "mööbl": "mööbel",
  "mööblipoodis": "mööblipoes",
  "müja": "müüja",
  "müjana": "müüjana",
  "müüaksin": "müüksin",
  "müüame": "müüme",
  "müüan": "müün",
  "müüana": "müüjana",
  "müüatakse": "müüakse",
  "müüavad": "müüvad",
  "müügiagentina": "müügiagendina",
  "müüjade": "müüjate",
  "müüjakse": "müüakse",
  "müüjan": "müün",
  "müüjavad": "müüvad",
  "naad": "nad",
  "nabrid": "naabrid",
  "nadal": "nädal",
  "nadala": "nädala",
  "nadalal": "nädalal",
  "nadalalõpul": "nädalalõpul",
  "nadalas": "nädalas",
  "nadalat": "nädalat",
  "nadalavahetus": "nädalavahetus",
  "nahkast": "nahast",
  "naidata": "näidata",
  "nainud": "näinud",
  "naisedel": "naistel",
  "naitab": "näitab",
  "naitavad": "näitavad",
  "naljasime": "naljatasime",
  "narkomanid": "narkomaanid",
  "narkootikumite": "narkootikumide",
  "nattuke": "natuke",
  "naudima": "nautima",
  "negativne": "negatiivne",
  "nei": "neil",
  "neie": "nende",
  "nelikümne": "neljakümne",
  "nelipäev": "neljapäev",
  "nelipäeval": "neljapäeval",
  "nelitoaline": "neljatoaline",
  "neljapaev": "neljapäev",
  "neljapaeval": "neljapäeval",
  "neljapäevati": "neljapäeviti",
  "nemadel": "nendel",
  "niimodi": "niimoodi",
  "niisaama": "niisama",
  "nimetakse": "nimetatakse",
  "nimoodi": "niimoodi",
  "nissugune": "niisugune",
  "nissugused": "niisugused",
  "nissuguseid": "niisuguseid",
  "nisugune": "niisugune",
  "nisugused": "niisugused",
  "noha": "näha",
  "noordest": "noortest",
  "nooredest": "noortest",
  "nooreid": "noori",
  "noorinimesed": "noored inimesed",
  "noorinimestel": "noortel inimestel",
  "norem": "noorem",
  "normalne": "normaalne",
  "normalselt": "normaalselt",
  "nortele": "noortele",
  "nous": "nõus",
  "nuber": "number",
  "nugaga": "noaga",
  "nuud": "nüüd",
  "nõrgamaks": "nõrgemaks",
  "nõuakse": "nõutakse",
  "nõukogudeajal": "nõukogude ajal",
  "nõutatakse": "nõutakse",
  "näenud": "näinud",
  "näes": "nägi",
  "näetame": "näeme",
  "nägal": "nädalal",
  "nägeb": "näeb",
  "nägeda": "näha",
  "nägesin": "nägin",
  "nägib": "näeb",
  "nägis": "nägi",
  "nägisid": "nägid",
  "nägisin": "nägin",
  "nägäla": "nädala",
  "näidab": "näitab",
  "näidavad": "näitavad",
  "näided": "näited",
  "näideks": "näiteks",
  "näine": "naine",
  "näitakse": "näidatakse",
  "näitanud": "näidanud",
  "näitek": "näiteks",
  "näitkes": "näiteks",
  "nääme": "näeme",
  "nöukogu": "nõukogu",
  "nüd": "nüüd",
  "nüüt": "nüüd",
  "odata": "oodata",
  "odavem": "odavam",
  "oige": "õige",
  "oleb": "on",
  "oleda": "olla",
  "oleksib": "oleks",
  "olem": "olen",
  "oliks": "oleks",
  "olis": "oli",
  "olivad": "olid",
  "olleks": "oleks",
  "omanikutele": "omanikele",
  "oodame": "ootame",
  "oodan": "ootan",
  "oodatan": "ootan",
  "oodate": "ootate",
  "oodavam": "odavam",
  "oopera": "ooper",
  "oosta": "osta",
  "ootada": "oodata",
  "ootage": "oodake",
  "ootake": "oodake",
  "opetaja": "õpetaja",
  "opib": "õpib",
  "opin": "õpin",
  "oppida": "õppida",
  "oppima": "õppima",
  "oppisin": "õppisin",
  "osalejade": "osalejate",
  "osavõtta": "osa võtta",
  "oskada": "osata",
  "oskanud": "osanud",
  "oskata": "osata",
  "ostada": "osta",
  "ostage": "ostke",
  "ostama": "ostma",
  "ostanud": "ostnud",
  "ostas": "ostis",
  "ostasid": "ostsid",
  "ostasime": "ostsime",
  "ostasin": "ostsin",
  "ostata": "osta",
  "ostatakse": "ostetakse",
  "ostid": "ostsid",
  "ostime": "ostsime",
  "ostin": "ostsin",
  "otab": "ootab",
  "otame": "ootame",
  "otan": "ootan",
  "otavad": "ootavad",
  "otselt": "otseselt",
  "otsusin": "otsustasin",
  "otta": "oota",
  "ottame": "ootame",
  "ottan": "ootan",
  "ovad": "on",
  "ovat": "olevat",
  "paegu": "praegu",
  "paeva": "päeva",
  "paevad": "päevad",
  "paevaks": "päevaks",
  "paeval": "päeval",
  "paike": "päike",
  "paistas": "paistis",
  "paisteline": "päikesepaisteline",
  "paistsis": "paistis",
  "paket": "pakett",
  "pakettis": "paketis",
  "pakkime": "pakime",
  "pakkin": "pakin",
  "pakkub": "pakub",
  "pakkuks": "pakuks",
  "pakkume": "pakume",
  "pakkun": "pakun",
  "pakkutakse": "pakutakse",
  "pakkute": "pakute",
  "pakkuti": "pakuti",
  "pakkutud": "pakutud",
  "pakuda": "pakkuda",
  "pakumine": "pakkumine",
  "pakus": "pakkus",
  "pakusid": "pakkusid",
  "pakusin": "pakkusin",
  "pakutab": "pakub",
  "pakutate": "pakute",
  "palavikk": "palavik",
  "palg": "palk",
  "paljem": "rohkem",
  "paljuid": "palju",
  "palkaga": "palgaga",
  "palkani": "palgani",
  "palkast": "palgast",
  "palkat": "palka",
  "paneda": "panna",
  "panesime": "panime",
  "pangades": "pankades",
  "pangasse": "panka",
  "pangis": "pangas",
  "pankad": "pangad",
  "pankakaart": "pangakaart",
  "pankalaenu": "pangalaenu",
  "pankale": "pangale",
  "pankas": "pangas",
  "pankast": "pangast",
  "pankis": "pangas",
  "pannaa": "panna",
  "pannid": "pannud",
  "pantud": "pandud",
  "parases": "parajas",
  "paremeni": "paremini",
  "paremine": "paremini",
  "pargides": "parkides",
  "pargisse": "parki",
  "pariks": "paariks",
  "parit": "pärit",
  "passivne": "passiivne",
  "passivseks": "passiivseks",
  "pastapliats": "pastapliiats",
  "patsientid": "patsiendid",
  "peasin": "pidin",
  "peerega": "perega",
  "pegel": "peegel",
  "pensionarid": "pensionärid",
  "pensionäär": "pensionär",
  "pensionääre": "pensionäre",
  "pensionäärid": "pensionärid",
  "pensionääridest": "pensionäridest",
  "pensioon": "pension",
  "pensiooni": "pensioni",
  "pensioonile": "pensionile",
  "peodel": "pidudel",
  "peodes": "pidudes",
  "peosid": "pidusid",
  "perekona": "perekonna",
  "pereliikmedele": "pereliikmetele",
  "periiod": "periood",
  "period": "periood",
  "periodi": "perioodi",
  "periodil": "perioodil",
  "personaal": "personal",
  "personaali": "personali",
  "pidab": "peab",
  "pidan": "pean",
  "pidata": "pidada",
  "pidis": "pidi",
  "piduda": "pidada",
  "piduga": "peoga",
  "pidul": "peol",
  "pidule": "peole",
  "pidus": "peos",
  "pidusi": "pidusid",
  "pidusin": "pidasin",
  "piidevalt": "pidevalt",
  "piirukad": "pirukad",
  "piisut": "pisut",
  "pikkad": "pikad",
  "pikkaks": "pikaks",
  "pikkal": "pikal",
  "pikkem": "pikem",
  "pild": "pilt",
  "pildeid": "pilte",
  "pillet": "pilet",
  "pilletid": "piletid",
  "piltid": "pildid",
  "piltil": "pildil",
  "pingiline": "pingeline",
  "pisavalt": "piisavalt",
  "plaanerin": "plaanin",
  "plaju": "palju",
  "planerida": "planeerida",
  "planime": "plaanime",
  "pliats": "pliiats",
  "pliatsid": "pliiatsid",
  "podides": "poodides",
  "poesse": "poodi",
  "pois": "poiss",
  "poissid": "poisid",
  "poissiga": "poisiga",
  "poliklinikus": "polikliinikus",
  "politika": "poliitika",
  "politseise": "politseisse",
  "polt": "poolt",
  "poodid": "poed",
  "poodis": "poes",
  "poodist": "poest",
  "poolnud": "polnud",
  "popularne": "populaarne",
  "populäärne": "populaarne",
  "positivne": "positiivne",
  "postiteel": "posti teel",
  "praaegu": "praegu",
  "praaktika": "praktika",
  "praaktiliselt": "praktiliselt",
  "praega": "praegu",
  "praeguni": "praeguseni",
  "praegy": "praegu",
  "praigu": "praegu",
  "prantuse": "prantsuse",
  "presidentiks": "presidendiks",
  "prestiizne": "prestiižne",
  "prioriteetiks": "prioriteediks",
  "prioritet": "prioriteet",
  "probleemed": "probleemid",
  "probleemeid": "probleeme",
  "probleemit": "probleemi",
  "problem": "probleem",
  "probleme": "probleeme",
  "problemeid": "probleeme",
  "problemi": "probleemi",
  "problemid": "probleemid",
  "problemidest": "probleemidest",
  "problemm": "probleem",
  "proekt": "projekt",
  "proekti": "projekti",
  "proektid": "projektid",
  "professionalne": "professionaalne",
  "prograam": "programm",
  "proobleem": "probleem",
  "proobleemid": "probleemid",
  "prooblem": "probleem",
  "prooblemi": "probleemi",
  "prooblemid": "probleemid",
  "proova": "proua",
  "protsentid": "protsendid",
  "protsentiga": "protsendiga",
  "prova": "proua",
  "provime": "proovime",
  "provin": "proovin",
  "prägu": "praegu",
  "prägul": "praegu",
  "psühhilise": "psüühilise",
  "psühholog": "psühholoog",
  "psühhologia": "psühholoogia",
  "psühhologid": "psühholoogid",
  "psüholoogia": "psühholoogia",
  "psühoolog": "psühholoog",
  "pudumise": "puudumise",
  "puhapäev": "pühapäev",
  "puhapäeval": "pühapäeval",
  "puhkada": "puhata",
  "puhkades": "puhates",
  "puhkanud": "puhanud",
  "puhkapäev": "puhkepäev",
  "puhkapäeval": "puhkepäeval",
  "puhkata": "puhata",
  "puhkepäevati": "puhkepäeviti",
  "puhkuda": "puhata",
  "puhkuma": "puhkama",
  "puhkusin": "puhkasin",
  "puudma": "puuduma",
  "puuid": "puid",
  "puut": "puud",
  "puutusin": "puudusin",
  "puuviljaid": "puuvilju",
  "puvilja": "puuvilja",
  "põlludel": "põldudel",
  "põllus": "põllul",
  "päevak": "päevaks",
  "päevat": "päeva",
  "päevatasime": "päevitasime",
  "päevatasin": "päevitasin",
  "päha": "paha",
  "päikepaisteline": "päiksepaisteline",
  "päistab": "paistab",
  "päistas": "paistis",
  "päiv": "päev",
  "päiva": "päeva",
  "päival": "päeval",
  "päkkapikk": "päkapikk",
  "pälju": "palju",
  "päras": "pärast",
  "pärsiorjusest": "pärisorjusest",
  "päräst": "pärast",
  "päval": "päeval",
  "pääsime": "pääsesime",
  "pöördan": "pöördun",
  "pühapaev": "pühapäev",
  "pühapaeval": "pühapäeval",
  "pühapäevati": "pühapäeviti",
  "pühepäeval": "pühapäeval",
  "pühkasin": "puhkasin",
  "pühkepäevadel": "puhkepäevad",
  "pühkepäeval": "puhkapäeval",
  "pühkepäevati": "puhkepäeviti",
  "püksidele": "pükstele",
  "püüdavad": "püüavad",
  "raagib": "räägib",
  "raakida": "rääkida",
  "raamatid": "raamatud",
  "raamatude": "raamatute",
  "raamatuit": "raamatuid",
  "radios": "raadios",
  "radiost": "raadiost",
  "radiot": "raadiot",
  "rahakooti": "rahakoti",
  "rahakot": "rahakott",
  "rahakottis": "rahakotis",
  "rahat": "raha",
  "rahavstele": "rahvastele",
  "rahuline": "rahulik",
  "rahuolu": "rahulolu",
  "rahv": "rahvas",
  "rahvade": "rahvaste",
  "rahvadel": "rahvastel",
  "rahvalaulad": "rahvalaulud",
  "rahvalaulas": "rahvalaulus",
  "rahvapalli": "rahvastepalli",
  "rahvasel": "rahvusel",
  "rahvasele": "rahvusele",
  "rahvaspord": "rahvasport",
  "rahvusmuusika": "rahvamuusika",
  "raiskata": "raisata",
  "rakse": "raske",
  "ramat": "raamat",
  "ramatu": "raamatu",
  "ramatud": "raamatud",
  "ramatuid": "raamatuid",
  "ramatut": "raamatute",
  "ravimed": "ravimid/ravimeid",
  "realne": "reaalne",
  "redeni": "reedeni",
  "reedani": "reedeni",
  "reedes": "reedel",
  "reemont": "remont",
  "reissi": "reisi",
  "reklaamiagentina": "reklaamiagendina",
  "reklameerida": "reklaamida",
  "reklami": "reklaami",
  "remond": "remont",
  "remonteerida": "remontida",
  "remontiga": "remondiga",
  "remoonti": "remonti",
  "represeeriti": "represseeriti",
  "restoraani": "restorani",
  "restoraanid": "restoranid",
  "restoraanides": "restoranides",
  "restoraanis": "restoranis",
  "restoranisse": "restorani",
  "resurse": "ressursse",
  "resursid": "ressursid",
  "rezhisöör": "režissöör",
  "reziim": "režiim",
  "rided": "riided",
  "rietus": "riietus",
  "rigi": "riigi",
  "riied": "riided",
  "riiest": "riidest",
  "riig": "riik",
  "riigide": "riikide",
  "riigidel": "riikidel",
  "riigides": "riikides",
  "riigidest": "riikidest",
  "riikas": "rikas",
  "riipub": "ripub",
  "riisk": "risk",
  "rikad": "rikkad",
  "rikaks": "rikkaks",
  "rikkub": "rikub",
  "rikkuvad": "rikuvad",
  "rohilised": "rohelised",
  "rohtud": "rohud",
  "romaantika": "romantika",
  "romaantiline": "romantiline",
  "roogid": "road",
  "rulikardin": "rullkardin",
  "ruttem": "rutem",
  "ruutmetrit": "ruutmeetrit",
  "rõivadesse": "rõivastesse",
  "rõmmu": "rõõmu",
  "rõmmus": "rõõmus",
  "rõmsa": "rõõmsa",
  "rõmsad": "rõõmsad",
  "rõmus": "rõõmus",
  "rõõmusad": "rõõmsad",
  "rägi": "räägi",
  "rägib": "räägib",
  "rägida": "rääkida",
  "rägima": "rääkima",
  "rägime": "räägime",
  "rägin": "räägin",
  "rägisime": "rääkisime",
  "rägisin": "rääkisin",
  "rägitakse": "räägitakse",
  "rägite": "räägite",
  "rägivad": "räägivad",
  "räkida": "rääkida",
  "räkima": "rääkima",
  "räkime": "räägime",
  "räkisid": "rääkisid",
  "räkkida": "rääkida",
  "räkkime": "räägime",
  "räkkisime": "rääkisime",
  "räske": "raske",
  "räägida": "rääkida",
  "räägike": "rääkige",
  "räägima": "rääkima",
  "räägimata": "rääkimata",
  "räägimist": "rääkimist",
  "rääginud": "rääkinud",
  "räägis": "rääkis",
  "räägisid": "rääkisid",
  "räägisime": "rääkisime",
  "räägisin": "rääkisin",
  "räägitatakse": "räägitakse",
  "räägites": "rääkides",
  "rääki": "räägi",
  "rääkib": "räägib",
  "rääkid": "räägid",
  "rääkin": "räägin",
  "rääkita": "rääkida",
  "rääkitakse": "räägitakse",
  "rääkiti": "räägiti",
  "saadama": "sadama",
  "saadatakse": "saadetakse",
  "saadke": "saatke",
  "saadsid": "saatsid",
  "saaime": "saime",
  "saaksa": "saksa",
  "saamal": "samal",
  "saamuti": "samuti",
  "saaremal": "saaremaal",
  "saas": "sai",
  "saatab": "saadab",
  "sad": "saad",
  "saib": "sai",
  "sajanud": "sadanud",
  "saksakeelt": "saksa keelt",
  "saksalased": "sakslased",
  "salon": "salong",
  "samasugusi": "samasuguseid",
  "samat": "sama",
  "sammuti": "samuti",
  "sata": "sada",
  "sate": "saate",
  "sattutakse": "satutakse",
  "savad": "saavad",
  "savutada": "saavutada",
  "seases": "seas",
  "seed": "need",
  "seeda": "seda",
  "seelepärast": "sellepärast",
  "seelist": "sellist",
  "seelle": "selle",
  "seellepärast": "sellepärast",
  "seisas": "seisis",
  "seisav": "seisev",
  "seisisid": "seisid",
  "seitsekümne": "seitsmekümne",
  "sekretaar": "sekretär",
  "sekretarina": "sekretärina",
  "sekretäär": "sekretär",
  "sektsionkapp": "sektsioonkapp",
  "sele": "selle",
  "selega": "sellega",
  "selepärast": "sellepärast",
  "selest": "sellest",
  "selgetada": "selgitada",
  "selik": "seelik",
  "selist": "sellist",
  "selleparast": "sellepärast",
  "sellepäras": "sellepärast",
  "sellepärst": "sellepärast",
  "sellesed": "sellised",
  "selleseid": "selliseid",
  "selleste": "selliste",
  "sellestes": "sellistes",
  "sellinne": "selline",
  "sellisi": "selliseid",
  "selllest": "sellest",
  "sellpärast": "sellepärast",
  "seminaar": "seminar",
  "seminaari": "seminari",
  "seminaaridel": "seminaridel",
  "seminaaris": "seminaris",
  "seminarit": "seminari",
  "seotada": "seostada",
  "seotatud": "seotud",
  "seotub": "seostub",
  "setse": "seitse",
  "sida": "seda",
  "siel": "seal",
  "siiamani": "siiamaani",
  "siinu": "sinu",
  "sija": "siia",
  "sis": "siis",
  "sisetulek": "sissetulek",
  "siski": "siiski",
  "siss": "siis",
  "sisseastuda": "sisse astuda",
  "sissekliima": "sisekliima",
  "sissepääse": "sissepääsu",
  "situatsion": "situatsioon",
  "sjukune": "sihukene",
  "sober": "sõber",
  "sobranna": "sõbranna",
  "soem": "soojem",
  "sofa": "sohva",
  "sohvoosid": "sovhoosid",
  "sohvooside": "sovhooside",
  "soidab": "sõidab",
  "soidame": "sõidame",
  "soidan": "sõidan",
  "soita": "sõita",
  "soitma": "sõitma",
  "soje": "soe",
  "sojem": "soojem",
  "sokkid": "sokid",
  "soobi": "sobi",
  "soobib": "sobib",
  "soobiks": "sobiks",
  "soobin": "sobin",
  "soobiv": "sobiv",
  "soobiva": "sobiva",
  "soobivad": "sobivad",
  "soobivat": "sobivat",
  "soodustarif": "soodustariif",
  "sooe": "soe",
  "soogiks": "söögiks",
  "soojed": "soojad",
  "soomi": "soome",
  "soomist": "söömist",
  "soostereotüüpid": "soostereotüübid",
  "soovitamatu": "soovimatu",
  "soovitega": "soovidega",
  "soritada": "sooritada",
  "soritan": "sooritan",
  "sotsiaaldemokraatid": "sotsiaaldemokraadid",
  "sotsiolism": "sotsialism",
  "sotsiolismi": "sotsialismi",
  "soviksin": "sooviksin",
  "sovin": "soovin",
  "spetsialiisteid": "spetsialiste",
  "spetsialiistid": "spetsialistid",
  "spetsialisteid": "spetsialiste",
  "spordilagris": "spordilaagris",
  "spordilagrist": "spordilaagrist",
  "sportiga": "spordiga",
  "staatistika": "statistika",
  "stadionil": "staadionil",
  "stadionile": "staadionile",
  "statiistika": "statistika",
  "sugulaseid": "sugulasi",
  "suhed": "suhted",
  "suheldada": "suhelda",
  "suhkelda": "suhelda",
  "suhtelda": "suhelda",
  "suhtleda": "suhelda",
  "suitsuvad": "suitsetavad",
  "sullega": "sinuga",
  "sundib": "sunnib",
  "sundivad": "sunnivad",
  "sunnipäev": "sünnipäev",
  "sunu": "sinu",
  "sunuga": "sinuga",
  "suppelda": "supelda",
  "surem": "suurem",
  "surepärane": "suurepärane",
  "surmud": "surnud",
  "surt": "suurt",
  "suuredes": "suurtes",
  "suureid": "suuri",
  "suureim": "suurim",
  "suurepäärane": "suurepärane",
  "suurnud": "surnud",
  "suvela": "suvel",
  "suvelas": "suvilas",
  "suvelasse": "suvilasse",
  "suvenirid": "suveniirid",
  "suvet": "suve",
  "suvil": "suvel",
  "suvillasse": "suvilasse",
  "suvimajas": "suvemajas",
  "sõbr": "sõber",
  "sõbrade": "sõprade",
  "sõbradega": "sõpradega",
  "sõbradeks": "sõpradeks",
  "sõbradel": "sõpradeks",
  "sõbradele": "sõpradele",
  "sõbradest": "sõpradest",
  "sõbradeta": "sõpradeta",
  "sõbraid": "sõpru",
  "sõbranaga": "sõbrannaga",
  "sõbratega": "sõpradega",
  "sõbru": "sõpru",
  "sõdab": "sõidab",
  "sõdame": "sõidame",
  "sõdan": "sõidan",
  "sõidada": "sõita",
  "sõidama": "sõitma",
  "sõidanud": "sõitnud",
  "sõidas": "sõitis",
  "sõidasid": "sõitsid",
  "sõidasime": "sõitsime",
  "sõidasin": "sõitsin",
  "sõidat": "sõidad",
  "sõidata": "sõita",
  "sõidis": "sõitis",
  "sõidma": "sõitma",
  "sõidnud": "sõitnud",
  "sõidsid": "sõitsid",
  "sõidsime": "sõitsime",
  "sõidsin": "sõitsin",
  "sõigame": "sõidame",
  "sõitab": "sõidab",
  "sõitada": "sõita",
  "sõitama": "sõitma",
  "sõitame": "sõidame",
  "sõitan": "sõidan",
  "sõitasime": "sõitsime",
  "sõitasin": "sõitsin",
  "sõitavad": "sõidavad",
  "sõitin": "sõitsin",
  "sõitme": "sõidame",
  "sõitsida": "sõita",
  "sõitsivad": "sõitsid",
  "sõitta": "sõita",
  "sõper": "sõber",
  "sõprad": "sõbrad",
  "sõpraga": "sõbraga",
  "sõprale": "sõbrale",
  "sõpranna": "sõbranna",
  "sõpratega": "sõpradega",
  "sõtsin": "sõitsin",
  "sään": "saan",
  "säästatakse": "säästetakse",
  "söber": "sõber",
  "söbraga": "sõbraga",
  "söime": "sõime",
  "söin": "sõin",
  "söömasime": "sõime",
  "söösin": "sõin",
  "sündib": "sünnib",
  "sündivad": "sünnivad",
  "sündmusid": "sündmused",
  "sünipäev": "sünnipäev",
  "sünipäevaks": "sünnipäevaks",
  "sünipäeval": "sünnipäeval",
  "sünipäevale": "sünnipäevale",
  "sünndinud": "sündinud",
  "sünnipaev": "sünnipäev",
  "sünnipaeva": "sünnipäeva",
  "sünnipaevaks": "sünnipäevaks",
  "sünnipaeval": "sünnipäeval",
  "sünnipaevale": "sünnipäevale",
  "sünnipävaks": "sünnipäevaks",
  "süzee": "süžee",
  "süzhee": "süžee",
  "süvel": "suvel",
  "süüja": "süüa",
  "süünipäev": "sünnipäev",
  "süüstem": "süsteem",
  "züriis": "žüriis",
  "züriist": "žüriist",
  "taabel": "tabel",
  "taabelis": "tabelis",
  "tabaka": "tubaka",
  "taega": "aega",
  "tagajargi": "tagajärgi",
  "tagisi": "tagasi",
  "tahak": "tahaks",
  "tahakse": "tahetakse",
  "tahaksi": "tahaks",
  "tahanud": "tahtnud",
  "tahas": "tahtis",
  "tahasin": "tahaksin",
  "tahelepanelik": "tähelepanelik",
  "tahelepanu": "tähelepanu",
  "tahendab": "tähendab",
  "tahksin": "tahaksin",
  "tahnud": "tahtnud",
  "tahsin": "tahtsin",
  "tahtan": "tahan",
  "tahtsam": "tähtsam",
  "taiskasvanud": "täiskasvanud",
  "taitsa": "täitsa",
  "tale": "talle",
  "tallina": "tallinna",
  "talllinnas": "Tallinnas",
  "talupojadele": "talupoegadele",
  "tana": "täna",
  "tanan": "tänan",
  "tanapaeval": "tänapäeval",
  "tanapäeval": "tänapäeval",
  "tanav": "tänav",
  "tanaval": "tänaval",
  "tansida": "tantsida",
  "tansime": "tantsime",
  "tansisime": "tantsisime",
  "tansivad": "tantsivad",
  "tansud": "tantsud",
  "tansukoolis": "tantsukoolis",
  "tansuks": "tantsuks",
  "tansust": "tantsust",
  "tantsidega": "tantsudega",
  "tantsiga": "tantsuga",
  "tantsist": "tantsust",
  "tappab": "tapab",
  "tappavad": "tapavad",
  "tapselt": "täpselt",
  "tarbitada": "tarbida",
  "targed": "targad",
  "tarkad": "targad",
  "tarkem": "targem",
  "tarkemaks": "targemaks",
  "tasel": "tasemel",
  "tasutu": "tasuta",
  "teadame": "teatame",
  "teadan": "teatan",
  "teama": "teadma",
  "teanud": "teadnud",
  "teas": "teadis",
  "teasin": "teadsin",
  "teatride": "teatrite",
  "teatrides": "teatrites",
  "teatridest": "teatritest",
  "teatrise": "teatrisse",
  "teatsin": "teadsin",
  "tede": "teda",
  "teegin": "tegin",
  "teelida": "tellida",
  "teem": "teema",
  "teemaid": "teemasid",
  "teenustepakketi": "teenusepaketti",
  "tegeb": "teeb",
  "tegeda": "teha",
  "tegeksin": "teeksin",
  "tegelekult": "tegelikult",
  "tegeme": "teeme",
  "tegen": "teen",
  "tegesin": "tegin",
  "tegis": "tegi",
  "tegisime": "tegime",
  "tegisin": "tegin",
  "tegud": "teod",
  "tehasi": "tehaseid",
  "teiel": "teil",
  "teiele": "teile",
  "teies": "teie",
  "teiga": "teiega",
  "teind": "teinud",
  "teined": "teised",
  "teines": "teises",
  "teineteistega": "teineteisega",
  "teiseid": "teisi",
  "teisepaeval": "teisipäeval",
  "teisepäev": "teisipäev",
  "teisepäeval": "teisipäeval",
  "teisepäevast": "teisipäevast",
  "teisipaev": "teisipäev",
  "teisipaeval": "teisipäeval",
  "teisipäevati": "teisipäeviti",
  "teismoodi": "teistmoodi",
  "teissugune": "teistsugune",
  "teistedel": "teistel",
  "teistedes": "teistes",
  "tekinud": "tekkinud",
  "tekis": "tekkis",
  "tekiv": "tekkiv",
  "tekkitab": "tekitab",
  "tekkitada": "tekitada",
  "tekkitas": "tekitas",
  "tekkitavad": "tekitavad",
  "telefonimüüa": "telefonimüüja",
  "telefonit": "telefoni",
  "telefoniteel": "telefoni teel",
  "telefoon": "telefon",
  "telefooni": "telefoni",
  "telefoonid": "telefonid",
  "telefooniga": "telefoniga",
  "telefoonil": "telefonil",
  "telefooninumber": "telefoninumber",
  "telefoonipoodides": "telefonipoodides",
  "televisionist": "teleivsioonist",
  "televisoorit": "televiisorit",
  "televisor": "televiisor",
  "televisorist": "televiisorist",
  "televisorit": "televiisorit",
  "telgides": "telkides",
  "telkid": "telgid",
  "tellimuseid": "tellimusi",
  "tellitatud": "tellitud",
  "temalle": "talle",
  "teoria": "teooria",
  "teretulemast": "tere tulemas",
  "territorium": "territoorium",
  "terveslik": "tervislik",
  "tevad": "teevad",
  "tingimatta": "tingimata",
  "toidupoodis": "toidupoes",
  "toitule": "toidule",
  "tolla": "tolle",
  "tooded": "tooted",
  "toodeid": "tooteid",
  "tootada": "töötada",
  "tooti": "toodi",
  "tortid": "tordid",
  "tortiga": "tordiga",
  "trennida": "treenida",
  "treppikoda": "trepikoda",
  "tribuline": "triibuline",
  "trükitatud": "trükitud",
  "tsari": "tsaari",
  "tua": "tuua",
  "tualet": "tualett",
  "tubad": "toad",
  "tubak": "tubakas",
  "tubakase": "tubaka",
  "tubas": "toas",
  "tudenge": "tudengeid",
  "tudruk": "tüdruk",
  "tudrukud": "tüdrukud",
  "tudrük": "tüdruk",
  "tuhad": "tuhat",
  "tuleda": "tulla",
  "tulemuseid": "tulemusi",
  "tulesime": "tulime",
  "tulesin": "tulin",
  "tulevikkus": "tulevikus",
  "tulevikuses": "tulevikus",
  "tulevikut": "tulevikku",
  "tulib": "tuleb",
  "tulisi": "tuli",
  "tulleb": "tuleb",
  "tulled": "tuled",
  "tullen": "tulen",
  "tundakse": "tuntakse",
  "tundid": "tunnid",
  "tundil": "tunnil",
  "tundit": "tundi",
  "tunen": "tunnen",
  "tunnakse": "tuntakse",
  "tunneid": "tundeid",
  "tunnes": "tundis",
  "tunnide": "tundide",
  "tunnides": "tundides",
  "tuntub": "tundub",
  "tupli": "tubli",
  "tutar": "tütar",
  "tutav": "tuttav",
  "tutavaid": "tuttavaid",
  "tuttvusin": "tutvusin",
  "tuudengeid": "tudengeid",
  "tuulevad": "tulevad",
  "tõlgijana": "tõlkijana",
  "tõlkin": "tõlgin",
  "tõsiline": "tõsine",
  "tõstama": "tõstma",
  "tõusan": "tõusen",
  "tõuses": "tõusis",
  "tõustab": "tõstab",
  "tõõta": "tööta",
  "täesti": "täiesti",
  "tähedab": "tähendab",
  "tähtisad": "tähtsad",
  "tähtisam": "tähtsam",
  "tähtist": "tähtsat",
  "tähtsem": "tähtsam",
  "täiskasvane": "täiskasvanud",
  "tänapaeval": "tänapäeval",
  "tänapäevadel": "tänapäeval",
  "tänapäevades": "tänapäeval",
  "tänavadel": "tänavatel",
  "tänän": "tänan",
  "täti": "tädi",
  "töd": "tööd",
  "töotab": "töötab",
  "tööda": "töötada",
  "töödata": "töötada",
  "töögrafik": "töögraafik",
  "tööitan": "töötan",
  "tööitavad": "töötavad",
  "töökaslastega": "töökaaslastega",
  "töökollektiv": "töökollektiiv",
  "tööma": "töötama",
  "töömest": "töömeest",
  "tööpaev": "tööpäev",
  "tööpaeval": "tööpäeval",
  "tööproblem": "tööprobleem",
  "tööpuduse": "tööpuuduse",
  "tööpuduste": "tööpuuduse",
  "töörist": "tööriist",
  "tööristad": "tööriistad",
  "tööristu": "tööriistu",
  "tööstaaz": "tööstaaž",
  "tööstaazi": "tööstaaži",
  "tööstuskaubaid": "tööstuskaupu",
  "tööstuskaupad": "tööstuskaubad",
  "tööt": "tööd",
  "töötaga": "töötada",
  "töötude": "töötute",
  "tütra": "tütre",
  "tütraga": "tütrega",
  "tütrale": "tütrele",
  "tütruk": "tüdruk",
  "tüttar": "tütar",
  "tüttu": "tüütu",
  "ued": "uued",
  "uesti": "uuesti",
  "uhe": "ühe",
  "ule": "üle",
  "ulikooli": "ülikooli",
  "ulikoolis": "ülikoolis",
  "umber": "ümber",
  "uskulised": "usulised",
  "usuda": "uskuda",
  "usuma": "uskuma",
  "usunud": "uskunud",
  "ususid": "uskusid",
  "ususin": "uskusin",
  "uudisi": "uudiseid",
  "uuede": "uute",
  "vaabrikud": "vabrikud",
  "vaadama": "vaatama",
  "vaadan": "vaatan",
  "vaadate": "vaatate",
  "vaadeti": "vaadati",
  "vaaldan": "valdan",
  "vaatada": "vaadata",
  "vaatades": "vaadates",
  "vaatage": "vaadake",
  "vaatanud": "vaadanud",
  "vaatisin": "vaatasin",
  "vabaabieluses": "vabaabielus",
  "vabaaeg": "vaba aeg",
  "vabaaega": "vaba aega",
  "vabaajal": "vabal ajal",
  "vabapäev": "vaba päev",
  "vadata": "vaadata",
  "vahem": "vähem",
  "vahemalt": "vähemalt",
  "vaide": "väide",
  "vaised": "vaesed",
  "vajalikuid": "vajalikke",
  "vajalikut": "vajalikku",
  "valaline": "vallaline",
  "valdada": "vallata",
  "valdata": "vallata",
  "validsin": "valisin",
  "valismaale": "välismaale",
  "valitsin": "valisin",
  "valub": "valutab",
  "vanaemat": "vanaema",
  "vanemade": "vanemate",
  "vanemadega": "vanematega",
  "vanemadel": "vanematel",
  "vanemadele": "vanematele",
  "vanemadest": "vanematest",
  "vanituba": "vannituba",
  "variantid": "variandid",
  "varst": "varsti",
  "varvi": "värvi",
  "vasamul": "vasakul",
  "vastada": "vastata",
  "vastage": "vastake",
  "vastuargumentid": "vastuargumendid",
  "vastuda": "vastata",
  "vastusi": "vastuseid",
  "vastustunnet": "vastutustunnet",
  "vastustustundlik": "vastutustundlik",
  "vastustustunne": "vastutustunnet",
  "vastustustunnega": "vastutustundega",
  "vastustustunnet": "vastutustunnet",
  "vatada": "vaadata",
  "vatama": "vaatama",
  "vatame": "vaatame",
  "vatamise": "vaatamise",
  "vatasime": "vaatasime",
  "vatasin": "vaatasin",
  "vatavad": "vaatavad",
  "vatta": "vaata",
  "vattada": "vaadata",
  "veedada": "veeta",
  "veedsime": "veetsime",
  "veedsin": "veetsin",
  "veenemaale": "venemaale",
  "veesi": "vesi",
  "veet": "vett",
  "veetab": "veedab",
  "veetame": "veedame",
  "vel": "veel",
  "vell": "veel",
  "vendunud": "veendunud",
  "venekeel": "vene keel",
  "venekeele": "vene keele",
  "venekeeles": "vene keeles",
  "venekeelt": "vene keelt",
  "venelaseid": "venelasi",
  "venemale": "venemaale",
  "verand": "veerand",
  "vettasid": "veetsid",
  "viendal": "viiendal",
  "viest": "viiest",
  "viieastane": "viieaastane",
  "viikingute": "viikingite",
  "viiskummend": "viiskümmend",
  "viiskümend": "viiskümmend",
  "vimase": "viimase",
  "vimasel": "viimasel",
  "visakad": "viisakad",
  "visakalt": "viisakalt",
  "visakas": "viisakas",
  "visiitkardi": "visiitkaardi",
  "visiitkart": "visiitkaart",
  "visiitkarti": "visiitkaarti",
  "visit": "visiit",
  "vodi": "voodi",
  "voib": "võib",
  "voileibu": "võileibu",
  "voimalust": "võimalust",
  "voime": "võime",
  "voivad": "võivad",
  "votta": "võtta",
  "võb": "võib",
  "võike": "väike",
  "võimaldus": "võimalus",
  "võimlaus": "võimalus",
  "võimlusi": "võimalusi",
  "võitelda": "võidelda",
  "võks": "võiks",
  "võrdsad": "võrdsed",
  "võreldes": "võrreldes",
  "võrgpall": "võrkpall",
  "võrgpalli": "võrkpalli",
  "võrkeele": "võõrkeele",
  "võrras": "võõras",
  "võrreldame": "võrdleme",
  "võrreldan": "võrdlen",
  "võtakse": "võetakse",
  "võtama": "võtma",
  "võtas": "võttis",
  "võtasin": "võtsin",
  "võtsit": "võtsid",
  "võttad": "võtad",
  "võttaks": "võtaks",
  "võttakse": "võetakse",
  "võttame": "võtame",
  "võttan": "võtan",
  "võttas": "võttis",
  "võttasime": "võtsime",
  "võttate": "võtate",
  "võttavad": "võtavad",
  "vägä": "väga",
  "vähetamine": "vähendamine",
  "väidasid": "väitsid",
  "väidega": "väitega",
  "väiked": "väiksed",
  "väikes": "väikses",
  "väikset": "väikest",
  "väiksete": "väikeste",
  "väjke": "väike",
  "väke": "väike",
  "välismaalis": "välismaal",
  "välismale": "välismaale",
  "välismalt": "välismaalt",
  "väljarännega": "väljarändega",
  "värsti": "varsti",
  "värtustavad": "väärtustavad",
  "vätega": "väitega",
  "vääga": "väga",
  "väälismaal": "välismaal",
  "väälismaale": "välismaale",
  "vöga": "väga",
  "vöib": "võib",
  "vöiks": "võiks",
  "wabariigis": "vabariigis",
  "õdega": "õega",
  "õdel": "õel",
  "õelda": "öelda",
  "õeldi": "öeldi",
  "õhkut": "õhku",
  "õhtudel": "õhtutel",
  "õhtuli": "õhtul",
  "õlud": "õlut",
  "õnelik": "õnnelik",
  "õnnestused": "õnnetused",
  "õnnet": "õnne",
  "õnnetleda": "õnnitleda",
  "õnnetlen": "õnnitlen",
  "õnnetlesid": "õnnitlesid",
  "õnnitlin": "õnnitlen",
  "õpeb": "õpib",
  "õpelane": "õpilane",
  "õpelased": "õpilased",
  "õpenguid": "õpinguid",
  "õpesin": "õppisin",
  "õpetajan": "õpetajana",
  "õpida": "õppida",
  "õpija": "õppija",
  "õpilaseid": "õpilasi",
  "õpima": "õppima",
  "õpimine": "õppimine",
  "õpimise": "õppimise",
  "õpimisega": "õppimisega",
  "õpimiseks": "õppimiseks",
  "õpimisest": "õppimisest",
  "õpimist": "õppimist",
  "õpinud": "õppinud",
  "õpis": "õppis",
  "õpisid": "õppisid",
  "õpisime": "õppisime",
  "õpisin": "õppisin",
  "õpitab": "õpetab",
  "õpitaja": "õpetaja",
  "õpitajad": "õpetajad",
  "õpitajana": "õpetajana",
  "õppenud": "õppinud",
  "õppesid": "õppisid",
  "õppesime": "õppisime",
  "õppesin": "õppisin",
  "õppetab": "õpetab",
  "õppetada": "õpetada",
  "õppetaja": "õpetaja",
  "õppetajad": "õpetajad",
  "õppetajana": "õpetajana",
  "õppetakse": "õpitakse",
  "õppetan": "õpetan",
  "õppetasid": "õpetasid",
  "õppetavad": "õpetavad",
  "õppevad": "õpivad",
  "õppib": "õpib",
  "õppid": "õpid",
  "õppik": "õpik",
  "õppiksin": "õpiksin",
  "õppikud": "õpikud",
  "õppilane": "õpilane",
  "õppilase": "õpilase",
  "õppilased": "õpilased",
  "õppilastele": "õpilastele",
  "õppime": "õpime",
  "õppin": "õpin",
  "õppinguid": "õpinguid",
  "õppisib": "õppis",
  "õppitada": "õpetada",
  "õppitaja": "õpetaja",
  "õppitakse": "õpitakse",
  "äitah": "aitäh",
  "äitahh": "aitäh",
  "äitäh": "aitäh",
  "äres": "ääres",
  "äripäevati": "äripäeviti",
  "ästi": "hästi",
  "öeltakse": "öeldakse",
  "ölda": "öelda",
  "ööelda": "öelda",
  "öölda": "öelda",
  "ööseni": "ööni",
  "üba": "juba",
  "üheksakummend": "üheksakümmend",
  "üheksakümend": "üheksakümmend",
  "üheltpoolt": "ühelt poolt",
  "üheneb": "ühineb/ühendab",
  "ühenemise": "ühinemise",
  "üheskonnas": "ühiskonnas",
  "ühiselamuses": "ühiselamus",
  "ühistranspordit": "ühistransporti",
  "ühistunnet": "ühtsustunnet",
  "üksed": "uksed",
  "üksele": "uksele",
  "üksest": "uksest",
  "üksina": "üksinda",
  "ülatus": "üllatus",
  "ülde": "üldse",
  "üldjoones": "üldjoontes",
  "üldselt": "üldiselt",
  "ülejaanud": "ülejäänud",
  "ülekooli": "ülikooli",
  "ülekoolis": "ülikoolis",
  "ülemaailma": "üle maailma",
  "ülesanned": "ülesanded",
  "ülesanneid": "ülesandeid",
  "ületöötada": "üle töötada",
  "ülikoolisse": "ülikooli",
  "üliõppilased": "üliõpilased",
  "ültse": "üldse",
  "ümberehitada": "ümber ehitada",
  "ümbes": "umbes",
  "ürituseid": "üritusi",
  "ütleda": "öelda",
  "ütleta": "ütelda",
  "ütletakse": "öeldakse",
  "üttelda": "ütelda",
  "üüritus": "üritus",
  "üüritused": "üritused",
  "yhe": "ühe",
  "yks": "üks"
}
